LICENSE
README.md
setup.cfg
setup.py
physicslib/__init__.py
physicslib/constants.py
physicslib/dimension.py
physicslib/formating.py
physicslib/physical.py
physicslib/unit.py
physicslib/vector.py
physicslib.egg-info/PKG-INFO
physicslib.egg-info/SOURCES.txt
physicslib.egg-info/dependency_links.txt
physicslib.egg-info/top_level.txt