Metadata-Version: 2.1
Name: physicslib
Version: 0.0.3a1
Summary: Library with physical objects and constants.
Home-page: https://github.com/NamorNiradnug/physicslib
Author: NamorNiradnug
Author-email: roma937a@mail.ru
License: MIT
Platform: UNKNOWN
Classifier: Programming Language :: Python :: 3
Classifier: License :: OSI Approved :: MIT License
Classifier: Operating System :: OS Independent
Requires-Python: >=3.6
